fimage/__init__.py
fimage/class_register.py
fimage/converters.py
fimage/exceptions.py
fimage/filters.py
fimage/fimage.py
fimage/image_array.py
fimage/presets.py
fimage-0.2.3.dist-info/LICENSE
fimage-0.2.3.dist-info/WHEEL
fimage-0.2.3.dist-info/METADATA
fimage-0.2.3.dist-info/RECORD
